aiou/__init__.py
aiou/dos/__init__.py
aiou/dos/access.py
aiou/dos/file.py
aiou/dos/path.py
aiou/http/__init__.py
aiou/http/client.py
aiou/http/session.py
aiou/mem/__init__.py
aiou/mem/cache.py
aiou/redis/__init__.py
aiou/redis/client.py
aiou-1.1.0.dist-info/METADATA
aiou-1.1.0.dist-info/WHEEL
aiou-1.1.0.dist-info/top_level.txt
aiou-1.1.0.dist-info/RECORD
