Metadata-Version: 2.1
Name: aiou
Version: 1.1.0
Summary: Async I/O Utils
Home-page: https://github.com/moky/wormhole/
Author: Albert Moky
Author-email: albert.moky@gmail.com
License: MIT
Classifier: Programming Language :: Python :: 3
Classifier: License :: OSI Approved :: MIT License
Classifier: Operating System :: OS Independent
Requires-Dist: aiofiles
Requires-Dist: redis
Requires-Dist: yarl
Requires-Dist: aiohttp
